README.md
setup.py
pyymatcher/__init__.py
pyymatcher/accel.cpp
pyymatcher/matcher.py
pyymatcher.egg-info/PKG-INFO
pyymatcher.egg-info/SOURCES.txt
pyymatcher.egg-info/dependency_links.txt
pyymatcher.egg-info/top_level.txt