Metadata-Version: 2.1
Name: pyymatcher
Version: 0.0.5
Summary: Implementation of pattern matching in Python(using gestalt approach)
Home-page: https://github.com/abdulniyaspm/pyymatcher
Author: Abdul Niyas P M
Author-email: abdulniyaspm@gmail.com
License: MIT
Keywords: pattern-matching,pyymatcher
Platform: UNKNOWN
Classifier: Intended Audience :: Developers
Classifier: Operating System :: OS Independent
Classifier: Programming Language :: Python
Classifier: Programming Language :: Python :: 3.6
Requires-Python: >=3.6
